pySEQTarget/SEQopts.py
pySEQTarget/SEQoutput.py
pySEQTarget/SEQuential.py
pySEQTarget/__init__.py
pySEQTarget/analysis/__init__.py
pySEQTarget/analysis/_hazard.py
pySEQTarget/analysis/_outcome_fit.py
pySEQTarget/analysis/_risk_estimates.py
pySEQTarget/analysis/_subgroup_fit.py
pySEQTarget/analysis/_survival_pred.py
pySEQTarget/data/__init__.py
pySEQTarget/error/__init__.py
pySEQTarget/error/_data_checker.py
pySEQTarget/error/_param_checker.py
pySEQTarget/expansion/__init__.py
pySEQTarget/expansion/_binder.py
pySEQTarget/expansion/_diagnostics.py
pySEQTarget/expansion/_dynamic.py
pySEQTarget/expansion/_mapper.py
pySEQTarget/expansion/_selection.py
pySEQTarget/helpers/__init__.py
pySEQTarget/helpers/_bootstrap.py
pySEQTarget/helpers/_col_string.py
pySEQTarget/helpers/_fix_categories.py
pySEQTarget/helpers/_format_time.py
pySEQTarget/helpers/_offloader.py
pySEQTarget/helpers/_output_files.py
pySEQTarget/helpers/_pad.py
pySEQTarget/helpers/_predict_model.py
pySEQTarget/helpers/_prepare_data.py
pySEQTarget/initialization/__init__.py
pySEQTarget/initialization/_censoring.py
pySEQTarget/initialization/_denominator.py
pySEQTarget/initialization/_numerator.py
pySEQTarget/initialization/_outcome.py
pySEQTarget/plot/__init__.py
pySEQTarget/plot/_survival_plot.py
pySEQTarget/weighting/__init__.py
pySEQTarget/weighting/_weight_bind.py
pySEQTarget/weighting/_weight_data.py
pySEQTarget/weighting/_weight_fit.py
pySEQTarget/weighting/_weight_offload.py
pySEQTarget/weighting/_weight_pred.py
pySEQTarget/weighting/_weight_stats.py
pyseqtarget-0.11.0.dist-info/licenses/LICENSE
pyseqtarget-0.11.0.dist-info/METADATA
pyseqtarget-0.11.0.dist-info/WHEEL
pyseqtarget-0.11.0.dist-info/top_level.txt
pyseqtarget-0.11.0.dist-info/RECORD
