Metadata-Version: 2.4
Name: pySEQTarget
Version: 0.11.0
Summary: Sequentially Nested Target Trial Emulation
Author-email: Ryan O'Dea <ryan.odea@psi.ch>, Alejandro Szmulewicz <aszmulewicz@hsph.harvard.edu>, Tom Palmer <tom.palmer@bristol.ac.uk>, Miguel Hernan <mhernan@hsph.harvard.edu>
Maintainer-email: Ryan O'Dea <ryan.odea@psi.ch>
License: MIT
Project-URL: Homepage, https://github.com/CausalInference/pySEQTarget
Project-URL: Repository, https://github.com/CausalInference/pySEQTarget
Project-URL: Bug Tracker, https://github.com/CausalInference/pySEQTarget/issues
Project-URL: Ryan O'Dea (ORCID), https://orcid.org/0009-0000-0103-9546
Project-URL: Alejandro Szmulewicz (ORCID), https://orcid.org/0000-0002-2664-802X
Project-URL: Tom Palmer (ORCID), https://orcid.org/0000-0003-4655-4511
Project-URL: Miguel Hernan (ORCID), https://orcid.org/0000-0003-1619-8456
Project-URL: University of Bristol (ROR), https://ror.org/0524sp257
Project-URL: Harvard University (ROR), https://ror.org/03vek6s52
Keywords: causal inference,sequential trial emulation,target trial,observational studies
Classifier: Development Status :: 4 - Beta
Classifier: Intended Audience :: Science/Research
Classifier: Programming Language :: Python :: 3
Classifier: Programming Language :: Python :: 3.10
Classifier: Programming Language :: Python :: 3.11
Classifier: Programming Language :: Python :: 3.12
Classifier: Programming Language :: Python :: 3.13
Classifier: Programming Language :: Python :: 3.14
Requires-Python: >=3.10
License-File: LICENSE
Requires-Dist: numpy
Requires-Dist: polars
Requires-Dist: tqdm
Requires-Dist: statsmodels
Requires-Dist: matplotlib
Requires-Dist: pyarrow
Requires-Dist: lifelines
Requires-Dist: joblib
Provides-Extra: output
Requires-Dist: markdown; extra == "output"
Requires-Dist: weasyprint; extra == "output"
Requires-Dist: tabulate; extra == "output"
Dynamic: license-file
